github_to_sops/__init__.py
github_to_sops-2.0.0.dist-info/licenses/LICENSE
github_to_sops-2.0.0.dist-info/METADATA
github_to_sops-2.0.0.dist-info/WHEEL
github_to_sops-2.0.0.dist-info/entry_points.txt
github_to_sops-2.0.0.dist-info/top_level.txt
github_to_sops-2.0.0.dist-info/RECORD
