Metadata-Version: 2.4
Name: github-to-sops
Version: 2.0.0
Summary: Standalone (no-dependencies beyond Python) script fetches SSH keys of GitHub repository contributors and generates SOPS-compatible SSH key files.
Author: Taras Glek
License: MIT
Project-URL: Homepage, https://github.com/tarasglek/github-to-sops
Project-URL: Changelog, https://github.com/tarasglek/github-to-sops/releases
Project-URL: Issues, https://github.com/tarasglek/github-to-sops/issues
Project-URL: CI, https://github.com/tarasglek/github-to-sops/actions
Classifier: License :: OSI Approved :: MIT License
Requires-Python: >=3.8
License-File: LICENSE
Dynamic: license-file
